control_broker/__init__.py
control_broker/py.typed
control_broker/_jsii/__init__.py
control_broker/_jsii/control-broker@0.12.3.jsii.tgz
control_broker-0.12.3.dist-info/LICENSE
control_broker-0.12.3.dist-info/METADATA
control_broker-0.12.3.dist-info/WHEEL
control_broker-0.12.3.dist-info/top_level.txt
control_broker-0.12.3.dist-info/RECORD
