Metadata-Version: 2.1
Name: control-broker
Version: 0.12.3
Summary: Control Broker allows customers to deploy an HTTP API on AWS that executes Policy as Code (PaC) policies using Open Policy Agent (OPA) or CloudFormation Guard to evaluate inputs and return decisions.
Home-page: https://github.com/VerticalRelevance/control-broker/
Author: Clark Schneider<cschneider@verticalrelevance.com>
License: Apache-2.0
Project-URL: Source, https://github.com/VerticalRelevance/control-broker.git
Classifier: Intended Audience :: Developers
Classifier: Operating System :: OS Independent
Classifier: Programming Language :: JavaScript
Classifier: Programming Language :: Python :: 3 :: Only
Classifier: Programming Language :: Python :: 3.7
Classifier: Programming Language :: Python :: 3.8
Classifier: Programming Language :: Python :: 3.9
Classifier: Programming Language :: Python :: 3.10
Classifier: Typing :: Typed
Classifier: Development Status :: 5 - Production/Stable
Classifier: License :: OSI Approved
Requires-Python: ~=3.7
License-File: LICENSE
Requires-Dist: aws-cdk-lib (<3.0.0,>=2.28.1)
Requires-Dist: aws-cdk.aws-apigatewayv2-alpha (==2.28.1.a0)
Requires-Dist: aws-cdk.aws-apigatewayv2-authorizers-alpha (==2.28.1.a0)
Requires-Dist: aws-cdk.aws-apigatewayv2-integrations-alpha (==2.28.1.a0)
Requires-Dist: aws-cdk.aws-lambda-python-alpha (==2.28.1.a0)
Requires-Dist: constructs (<11.0.0,>=10.0.5)
Requires-Dist: jsii (<2.0.0,>=1.61.0)
Requires-Dist: publication (>=0.0.3)
